.DS_Store
pyhsslms/__init__.py
pyhsslms/compat.py
pyhsslms/hsslms.py
pyhsslms/pyhsslms.py
pyhsslms-1.1.1.dist-info/LICENSE.txt
pyhsslms-1.1.1.dist-info/METADATA
pyhsslms-1.1.1.dist-info/WHEEL
pyhsslms-1.1.1.dist-info/entry_points.txt
pyhsslms-1.1.1.dist-info/top_level.txt
pyhsslms-1.1.1.dist-info/zip-safe
pyhsslms-1.1.1.dist-info/RECORD
